druid_query/__init__.py
druid_query/client.py
druid_query/utils.py
druid_query/components/__init__.py
druid_query/components/aggregations.py
druid_query/components/context.py
druid_query/components/data_sources.py
druid_query/components/dimension_specs.py
druid_query/components/druid_types.py
druid_query/components/extraction_functions.py
druid_query/components/filters.py
druid_query/components/granularities.py
druid_query/components/having_specs.py
druid_query/components/intervals.py
druid_query/components/limit_specs.py
druid_query/components/lookups.py
druid_query/components/post_aggregations.py
druid_query/components/search_query_specs.py
druid_query/components/to_include.py
druid_query/components/topn_metric_specs.py
druid_query/components/virtual_columns.py
druid_query/queries/__init__.py
druid_query-0.3.1.dist-info/LICENSE
druid_query-0.3.1.dist-info/METADATA
druid_query-0.3.1.dist-info/WHEEL
druid_query-0.3.1.dist-info/top_level.txt
druid_query-0.3.1.dist-info/RECORD
