Metadata-Version: 2.1
Name: druid-query
Version: 0.3.1
Summary: Apache Druid querying client library
Home-page: https://github.com/scimas/druid_query
Author: Mihir Gadgil
Project-URL: Bug Tracker, http://github.com/scimas/druid_query/issues
Classifier: Programming Language :: Python :: 3
Classifier: License :: OSI Approved :: MIT License
Requires-Python: >=3.9
License-File: LICENSE
Requires-Dist: httpx (==0.23.0)
